flagdataset/__init__.py
flagdataset/baai_config.py
flagdataset/baai_environment.py
flagdataset/baai_meta.py
flagdataset/baai_network.py
flagdataset/cmd/__init__.py
flagdataset/cmd/argument.py
flagdataset/cmd/run_option.py
flagdataset/core/__init__.py
flagdataset/core/baai_share_url.py
flagdataset/helper/__init__.py
flagdataset/helper/baai_dataset.py
flagdataset/helper/baai_jwtsign.py
flagdataset/helper/baai_logger.py
flagdataset/helper/baai_login.py
flagdataset/helper/baai_pbar.py
flagdataset/helper/baai_print.py
flagdataset/helper/baai_read.py
flagdataset/helper/baai_requests.py
flagdataset/helper/baai_update.py
flagdataset/sdk/__init__.py
flagdataset-1.2.8.dist-info/METADATA
flagdataset-1.2.8.dist-info/WHEEL
flagdataset-1.2.8.dist-info/entry_points.txt
flagdataset-1.2.8.dist-info/RECORD
