Metadata-Version: 2.3
Name: flagdataset
Version: 1.2.8
Summary: 
License: MIT
Author: shihongguang
Author-email: hgshi@baai.ac.cn
Requires-Python: >=3.10,<4.0
Classifier: License :: OSI Approved :: MIT License
Classifier: Programming Language :: Python :: 3
Classifier: Programming Language :: Python :: 3.10
Classifier: Programming Language :: Python :: 3.11
Classifier: Programming Language :: Python :: 3.12
Classifier: Programming Language :: Python :: 3.13
Requires-Dist: baai-flagdataset-ks3util (>=0.1.6)
Requires-Dist: msgpack (>=1.1.1,<2.0.0)
Requires-Dist: psutil (>=7.1.0,<8.0.0)
Requires-Dist: pyjwt (>=2.10.1,<3.0.0)
Requires-Dist: requests (>=2.32.3,<3.0.0)
